{
  "generated_at": "2026-07-22T15:40:25.745318+00:00",
  "generated_at_br": "22/07/2026 12:40",
  "cbbi": {
    "picycle": {
      "label": "Pi Cycle Top",
      "score": 37.3,
      "as_of": 1784592000
    },
    "rupl": {
      "label": "NUPL / RUPL",
      "score": 40.0,
      "as_of": 1784592000
    },
    "rhodl": {
      "label": "RHODL Ratio",
      "score": 19.4,
      "as_of": 1784592000
    },
    "puell": {
      "label": "Múltiplo de Puell",
      "score": 68.5,
      "as_of": 1784592000
    },
    "2yma": {
      "label": "Média Móvel 2 Anos",
      "score": 46.9,
      "as_of": 1784592000
    },
    "trolololo": {
      "label": "Trolololo Trend Line",
      "score": 19.0,
      "as_of": 1784592000
    },
    "mvrv": {
      "label": "MVRV Z-Score",
      "score": 18.1,
      "as_of": 1784592000
    },
    "reserverisk": {
      "label": "Reserve Risk",
      "score": 21.0,
      "as_of": 1784592000
    },
    "woobull": {
      "label": "Top Cap vs CVDD",
      "score": 30.0,
      "as_of": 1784592000
    },
    "confidence": {
      "label": "CBBI (confiança de topo)",
      "score": 33.4,
      "as_of": 1784592000
    }
  },
  "models": {
    "price": 65947,
    "ath": 124824.4537,
    "drawdown_from_ath": -47.16820459034783,
    "ma200": 72820.670823,
    "mayer_multiple": 0.9056082463218811,
    "ma730": 87468.39895342466,
    "ma730_multiple": 0.7539522935033438,
    "ma111": 70147.46144144144,
    "pi_cycle_top_line": 173207.23321885715,
    "pi_cycle_gap_pct": -59.500847546703696,
    "ytd_pct": -25.6384037250876,
    "stoch_rsi": {
      "value": 95.3,
      "k": 95.3,
      "d": 89.0,
      "rsi": 61.1,
      "zone": "sobrecomprado"
    }
  },
  "cycle": {
    "last_halving": "2024-04-20",
    "days_since_halving": 823,
    "next_halving_block": 1050000,
    "blocks_to_halving": 90855,
    "est_next_halving": "2028-04-13"
  },
  "market": {
    "btc": {
      "price": 65947,
      "chg24h": -0.9946947133639852,
      "chg7d": 0.8590417724265496,
      "chg30d": 1.6302074600950605,
      "chg1y": -44.444030475764286,
      "mcap": 1322878694665
    },
    "alts": [
      {
        "symbol": "ETH",
        "name": "Ethereum",
        "note": null,
        "vs_btc_focus": false,
        "price": 1941.96,
        "mcap": 234360966170,
        "chg24h": 0.7712275795919329,
        "chg7d": 0.5659084215025842,
        "chg30d": 10.8287256241629,
        "chg1y": -46.981582464025514,
        "price_btc": 0.02944233,
        "chg7d_btc": -0.3755540144125559,
        "chg30d_btc": 9.008624773699179
      },
      {
        "symbol": "BNB",
        "name": "BNB",
        "note": null,
        "vs_btc_focus": false,
        "price": 572.07,
        "mcap": 76179848409,
        "chg24h": -0.47232915887747745,
        "chg7d": -1.5188625189014042,
        "chg30d": -4.189380382831959,
        "chg1y": -24.97821775946444,
        "price_btc": 0.00867319,
        "chg7d_btc": -2.4408080672481387,
        "chg30d_btc": -5.762844205199019
      },
      {
        "symbol": "SOL",
        "name": "Solana",
        "note": null,
        "vs_btc_focus": false,
        "price": 78.49,
        "mcap": 45740547363,
        "chg24h": 0.7031815468888275,
        "chg7d": 0.5589389674672945,
        "chg30d": 6.756991778485151,
        "chg1y": -60.75540504653375,
        "price_btc": 0.00119001,
        "chg7d_btc": -0.2785334448108407,
        "chg30d_btc": 5.102242145166076
      },
      {
        "symbol": "HYPE",
        "name": "Hyperliquid",
        "note": null,
        "vs_btc_focus": false,
        "price": 58.48,
        "mcap": 13009320709,
        "chg24h": -5.260048148474873,
        "chg7d": -14.47008381774263,
        "chg30d": -14.599183484405867,
        "chg1y": 32.41227281082685,
        "price_btc": 0.00088663,
        "chg7d_btc": -15.182391902559218,
        "chg30d_btc": -15.923061022597205
      },
      {
        "symbol": "ZEC",
        "name": "Zcash",
        "note": null,
        "vs_btc_focus": false,
        "price": 515.9,
        "mcap": 8662551203,
        "chg24h": -4.32782829255424,
        "chg7d": -10.312594416971715,
        "chg30d": 13.59238139608335,
        "chg1y": 1113.9435659952735,
        "price_btc": 0.00782166,
        "chg7d_btc": -11.05952679986895,
        "chg30d_btc": 11.781169666432115
      },
      {
        "symbol": "AAVE",
        "name": "Aave",
        "note": null,
        "vs_btc_focus": false,
        "price": 97.54,
        "mcap": 1503419510,
        "chg24h": 2.796650793027093,
        "chg7d": 0.028417219030410914,
        "chg30d": 30.077217074982208,
        "chg1y": -68.12917915098927,
        "price_btc": 0.00147879,
        "chg7d_btc": -0.8416308860502569,
        "chg30d_btc": 28.06076907199897
      },
      {
        "symbol": "ONDO",
        "name": "Ondo",
        "note": null,
        "vs_btc_focus": false,
        "price": 0.416832,
        "mcap": 2029177050,
        "chg24h": 2.7005504864019425,
        "chg7d": 24.70064252460975,
        "chg30d": 23.661043992616147,
        "chg1y": -59.92546054198733,
        "price_btc": 6.32e-06,
        "chg7d_btc": 23.014222719965485,
        "chg30d_btc": 21.744059060028043
      },
      {
        "symbol": "MORPHO",
        "name": "Morpho",
        "note": null,
        "vs_btc_focus": false,
        "price": 1.97,
        "mcap": 1294494903,
        "chg24h": -2.230994251662578,
        "chg7d": -4.5476753595555985,
        "chg30d": 7.951814867410987,
        "chg1y": 1.125588111671564,
        "price_btc": 2.994e-05,
        "chg7d_btc": -5.863313505293479,
        "chg30d_btc": 6.278353315859422
      },
      {
        "symbol": "AERO",
        "name": "Aerodrome",
        "note": null,
        "vs_btc_focus": false,
        "price": 0.429308,
        "mcap": 417904948,
        "chg24h": -4.864867119824729,
        "chg7d": -17.198358562596823,
        "chg30d": -20.914704731927184,
        "chg1y": -54.76992499313609,
        "price_btc": 6.51e-06,
        "chg7d_btc": -18.339629856042116,
        "chg30d_btc": -21.485980471714434
      },
      {
        "symbol": "CFG",
        "name": "Centrifuge",
        "note": null,
        "vs_btc_focus": false,
        "price": 0.189675,
        "mcap": 0.0,
        "chg24h": 1.035818744512328,
        "chg7d": 6.6696169377696775,
        "chg30d": -17.712219248002246,
        "chg1y": -17.3936790545911,
        "price_btc": 2.88e-06,
        "chg7d_btc": 5.7697667589314445,
        "chg30d_btc": -18.996635974977654
      },
      {
        "symbol": "EVA",
        "name": "EverValue Coin",
        "note": "Lastreado em WBTC com burn vault — a leitura relevante é EVA/BTC.",
        "vs_btc_focus": true,
        "price": 34.75,
        "mcap": 0.0,
        "chg24h": -0.02503551477761941,
        "chg7d": 1.1966636161981465,
        "chg30d": 4.812844453591464,
        "chg1y": 1347.3670223737215,
        "price_btc": 0.00052684,
        "chg7d_btc": 0.1947563703081127,
        "chg30d_btc": 3.1770240081831798
      }
    ],
    "dominance": {
      "btc": 56.63745682104373,
      "eth": 10.039933340280193
    },
    "total_mcap": 2336527483041.5615,
    "total_mcap_chg24h": -0.607795953962822
  },
  "derivatives": {
    "funding_rate_pct": 0.00114359368856,
    "next_funding": "1784764800000",
    "open_interest_btc": 31057.694600000144,
    "open_interest_usd": 2048270487.7173095,
    "mark_price": 65929.8
  },
  "fear_greed": {
    "value": 33,
    "label": "Fear",
    "previous": 25
  },
  "altseason": {
    "value": 51.0,
    "source": "CMC (top 100)",
    "note": "0-25 temporada do BTC · 75-100 temporada de alts"
  },
  "etf": {
    "BTC": {
      "last_day": 203.0,
      "last_date": null,
      "week": 749.0,
      "month": -1617.0,
      "cumulative": null,
      "unit": "US$ mi"
    }
  },
  "etf_links": {
    "CoinGlass": "https://www.coinglass.com/pt/etf",
    "SoSoValue": "https://sosovalue.com/pt/assets/etf/us-btc-spot",
    "Farside": "https://farside.co.uk/btc/"
  },
  "insights": {
    "resumo": "Sinais mistos: indicadores quentes e frios convivem. Momentos assim pedem acompanhar qual lado ganha força.",
    "observacoes": [
      {
        "tag": "ciclo",
        "temp": "neutro",
        "texto": "CBBI em 33/100 — meio da faixa, sem extremo de ciclo."
      },
      {
        "tag": "preço",
        "temp": "frio",
        "texto": "Múltiplo de Mayer em 0.91 (<1): preço abaixo da média de 200 dias, território historicamente barato."
      },
      {
        "tag": "momentum",
        "temp": "quente",
        "texto": "Stoch RSI em 95 (sobrecomprado): momentum esticado para cima no curto prazo."
      }
    ],
    "disclaimer": "Leitura descritiva dos dados, não recomendação de compra ou venda."
  },
  "network": {
    "block_height": 959145,
    "hashrate": 878616682991351600000,
    "difficulty": 127170500429035.2,
    "difficulty_change_pct": -0.7145640046410273,
    "blocks_to_retarget": 471,
    "fee_fast": 1,
    "fee_economy": 1
  },
  "macro": null,
  "sources": {
    "CBBI": {
      "ok": true,
      "detail": "ok"
    },
    "CoinGecko": {
      "ok": true,
      "detail": "ok"
    },
    "OKX (derivativos)": {
      "ok": true,
      "detail": "ok"
    },
    "Fear & Greed": {
      "ok": true,
      "detail": "ok"
    },
    "mempool.space": {
      "ok": true,
      "detail": "ok"
    },
    "Stooq (macro)": {
      "ok": false,
      "detail": "RuntimeError: Stooq: nenhum símbolo válido (^spx,^ndq,^dji,dx.f,xauusd,10usy.b)"
    },
    "Altcoin Season (CMC)": {
      "ok": true,
      "detail": "ok"
    },
    "ETF (BTC via WalletPilot)": {
      "ok": true,
      "detail": "ok"
    },
    "ETF (CoinGlass)": {
      "ok": false,
      "detail": "RuntimeError: sem COINGLASS_API_KEY (opcional) — usando só WalletPilot"
    }
  }
}